mlfmu/__init__.py
mlfmu/api.py
mlfmu/py.typed
mlfmu/cli/__init__.py
mlfmu/cli/mlfmu.py
mlfmu/cli/publish_docs.py
mlfmu/fmu_build/CMakeLists.txt
mlfmu/fmu_build/conanfile.txt
mlfmu/fmu_build/cmake/FindFMUComplianceChecker.cmake
mlfmu/fmu_build/cmake/GenerateFmuGuid.cmake
mlfmu/fmu_build/cmake/ZipAll.cmake
mlfmu/fmu_build/cmake/fmu-uuid.h.in
mlfmu/fmu_build/cppfmu/.editorconfig
mlfmu/fmu_build/cppfmu/.git
mlfmu/fmu_build/cppfmu/.gitattributes
mlfmu/fmu_build/cppfmu/.gitignore
mlfmu/fmu_build/cppfmu/CMakeLists.txt
mlfmu/fmu_build/cppfmu/LICENCE.txt
mlfmu/fmu_build/cppfmu/README.md
mlfmu/fmu_build/cppfmu/conanfile.py
mlfmu/fmu_build/cppfmu/cppfmu_common.hpp
mlfmu/fmu_build/cppfmu/cppfmu_cs.cpp
mlfmu/fmu_build/cppfmu/cppfmu_cs.hpp
mlfmu/fmu_build/cppfmu/fmi_functions.cpp
mlfmu/fmu_build/cppfmu/version.txt
mlfmu/fmu_build/cppfmu/.github/workflows/ci-conan-gcc.yml
mlfmu/fmu_build/cppfmu/.github/workflows/ci-conan-msvc.yml
mlfmu/fmu_build/cppfmu/test_package/CMakeLists.txt
mlfmu/fmu_build/cppfmu/test_package/conanfile.py
mlfmu/fmu_build/cppfmu/test_package/main.cpp
mlfmu/fmu_build/cppfmu/tests/cs_slave.cpp
mlfmu/fmu_build/cppfmu/tests/cs_test.cpp
mlfmu/fmu_build/fmi/fmi2FunctionTypes.h
mlfmu/fmu_build/fmi/fmi2Functions.h
mlfmu/fmu_build/fmi/fmi2TypesPlatform.h
mlfmu/fmu_build/fmi/fmiFunctions.h
mlfmu/fmu_build/fmi/fmiPlatformTypes.h
mlfmu/fmu_build/templates/fmu/fmu_template.cpp
mlfmu/fmu_build/templates/fmu/model_definitions_template.h
mlfmu/fmu_build/templates/onnx_fmu/onnxFmu.cpp
mlfmu/fmu_build/templates/onnx_fmu/onnxFmu.hpp
mlfmu/types/__init__.py
mlfmu/types/fmu_component.py
mlfmu/types/onnx_model.py
mlfmu/utils/__init__.py
mlfmu/utils/builder.py
mlfmu/utils/fmi_builder.py
mlfmu/utils/interface.py
mlfmu/utils/logging.py
mlfmu/utils/path.py
mlfmu/utils/signals.py
mlfmu/utils/strings.py
mlfmu-1.0.3.dist-info/METADATA
mlfmu-1.0.3.dist-info/WHEEL
mlfmu-1.0.3.dist-info/entry_points.txt
mlfmu-1.0.3.dist-info/licenses/LICENSE
mlfmu-1.0.3.dist-info/licenses/LICENSE_THIRD_PARTY
mlfmu-1.0.3.dist-info/RECORD
