Metadata-Version: 2.4
Name: mlfmu
Version: 1.0.3
Summary: Export ML models represented as ONNX files to Functional-Mockup-Units (FMU)
Project-URL: Homepage, https://github.com/dnv-opensource/mlfmu
Project-URL: Documentation, https://dnv-opensource.github.io/mlfmu/README.html
Project-URL: Repository, https://github.com/dnv-opensource/mlfmu.git
Project-URL: Issues, https://github.com/dnv-opensource/mlfmu/issues
Project-URL: Changelog, https://github.com/dnv-opensource/mlfmu/blob/main/CHANGELOG.md
Author-email: Jorge Luis Mendez <jorge.luis.mendez@dnv.com>, Kristoffer Skare <kristoffer.skare@dnv.com>
Maintainer-email: Kristoffer Skare <kristoffer.skare@dnv.com>, Jorge Luis Mendez <jorge.luis.mendez@dnv.com>, Hee Jong Park <hee.jong.park@dnv.com>, Claas Rostock <claas.rostock@dnv.com>
License: BSD 3-Clause License
License-File: LICENSE
License-File: LICENSE_THIRD_PARTY
Classifier: Development Status :: 3 - Alpha
Classifier: Environment :: Console
Classifier: Intended Audience :: Developers
Classifier: Intended Audience :: Science/Research
Classifier: License :: OSI Approved :: BSD License
Classifier: Operating System :: Microsoft :: Windows
Classifier: Operating System :: POSIX :: Linux
Classifier: Programming Language :: Python :: 3.10
Classifier: Programming Language :: Python :: 3.11
Classifier: Programming Language :: Python :: 3.12
Classifier: Topic :: Scientific/Engineering
Classifier: Topic :: Software Development :: Libraries :: Python Modules
Requires-Python: <3.13,>=3.10
Requires-Dist: conan>=2.1
Requires-Dist: dictio>=0.3.4
Requires-Dist: json-schema-for-humans>=0.4.7
Requires-Dist: onnxruntime==1.18.1
Requires-Dist: pydantic>=2.6
